goal_plot/__init__.py
goal_plot/draw.py
goal_plot-0.1.dist-info/METADATA
goal_plot-0.1.dist-info/WHEEL
goal_plot-0.1.dist-info/top_level.txt
goal_plot-0.1.dist-info/RECORD
